{".class": "MypyFile", "_fullname": "models.skeletons", "is_partial_stub_package": false, "is_stub": false, "names": {".class": "SymbolTable", "HybridEncoderRegressor": {".class": "SymbolTableNode", "kind": "Gdef", "node": {".class": "TypeInfo", "_promote": null, "abstract_attributes": [], "bases": ["builtins.object"], "declared_metaclass": null, "defn": {".class": "ClassDef", "fullname": "models.skeletons.HybridEncoderRegressor", "name": "HybridEncoderRegressor", "type_vars": []}, "flags": ["fallback_to_any"], "fullname": "models.skeletons.HybridEncoderRegressor", "metaclass_type": null, "metadata": {}, "module_name": "models.skeletons", "mro": ["models.skeletons.HybridEncoderRegressor", "builtins.object"], "names": {".class": "SymbolTable", "__init__": {".class": "SymbolTableNode", "kind": "Mdef", "node": {".class": "FuncDef", "arg_kinds": [0, 0, 0, 0, 4], "arg_names": ["self", "encoder", "transformer", "decoder", "kwargs"], "flags": [], "fullname": "models.skeletons.HybridEncoderRegressor.__init__", "name": "__init__", "type": null}}, "call": {".class": "SymbolTableNode", "kind": "Mdef", "node": {".class": "FuncDef", "arg_kinds": [0, 0, 4], "arg_names": ["self", "x", "kwargs"], "flags": [], "fullname": "models.skeletons.HybridEncoderRegressor.call", "name": "call", "type": null}}, "decoder": {".class": "SymbolTableNode", "implicit": true, "kind": "Mdef", "node": {".class": "Var", "flags": [], "fullname": "models.skeletons.HybridEncoderRegressor.decoder", "name": "decoder", "type": {".class": "AnyType", "missing_import_name": null, "source_any": null, "type_of_any": 1}}}, "encoder": {".class": "SymbolTableNode", "implicit": true, "kind": "Mdef", "node": {".class": "Var", "flags": [], "fullname": "models.skeletons.HybridEncoderRegressor.encoder", "name": "encoder", "type": {".class": "AnyType", "missing_import_name": null, "source_any": null, "type_of_any": 1}}}, "transformer": {".class": "SymbolTableNode", "implicit": true, "kind": "Mdef", "node": {".class": "Var", "flags": [], "fullname": "models.skeletons.HybridEncoderRegressor.transformer", "name": "transformer", "type": {".class": "AnyType", "missing_import_name": null, "source_any": null, "type_of_any": 1}}}}, "tuple_type": null, "type_vars": [], "typeddict_type": null}}, "SUPPORTED_SKELETONS": {".class": "SymbolTableNode", "kind": "Gdef", "node": {".class": "Var", "flags": [], "fullname": "models.skeletons.SUPPORTED_SKELETONS", "name": "SUPPORTED_SKELETONS", "type": {".class": "Instance", "args": ["builtins.str", {".class": "CallableType", "arg_kinds": [0, 0, 0, 4], "arg_names": ["encoder", "transformer", "decoder", "kwargs"], "arg_types": [{".class": "AnyType", "missing_import_name": null, "source_any": null, "type_of_any": 1}, {".class": "AnyType", "missing_import_name": null, "source_any": null, "type_of_any": 1}, {".class": "AnyType", "missing_import_name": null, "source_any": null, "type_of_any": 1}, {".class": "AnyType", "missing_import_name": null, "source_any": null, "type_of_any": 1}], "bound_args": [null], "def_extras": {}, "fallback": "builtins.type", "implicit": true, "is_ellipsis_args": false, "name": "HybridEncoderRegressor", "ret_type": "models.skeletons.HybridEncoderRegressor", "variables": []}], "type_ref": "builtins.dict"}}}, "__doc__": {".class": "SymbolTableNode", "kind": "Gdef", "node": {".class": "Var", "flags": ["is_ready"], "fullname": "models.skeletons.__doc__", "name": "__doc__", "type": "builtins.str"}}, "__file__": {".class": "SymbolTableNode", "kind": "Gdef", "node": {".class": "Var", "flags": ["is_ready"], "fullname": "models.skeletons.__file__", "name": "__file__", "type": "builtins.str"}}, "__name__": {".class": "SymbolTableNode", "kind": "Gdef", "node": {".class": "Var", "flags": ["is_ready"], "fullname": "models.skeletons.__name__", "name": "__name__", "type": "builtins.str"}}, "__package__": {".class": "SymbolTableNode", "kind": "Gdef", "node": {".class": "Var", "flags": ["is_ready"], "fullname": "models.skeletons.__package__", "name": "__package__", "type": "builtins.str"}}, "tkm": {".class": "SymbolTableNode", "kind": "Gdef", "node": {".class": "Var", "flags": ["is_suppressed_import", "is_ready"], "fullname": "models.skeletons.tkm", "name": "tkm", "type": {".class": "AnyType", "missing_import_name": "models.skeletons.tkm", "source_any": null, "type_of_any": 3}}}}, "path": "/home/tallec/DL_ISIR_ABAW3/src/models/skeletons.py"}